{
  "pending": [
    {
      "id": "community_325821",
      "username": "nswer_change_up",
      "text": "nswer_change_up",
      "url": "https://www.threads.com/@nswer_change_up/post/DY2Mpgfkvnn",
      "date": "2026/05/28",
      "source": "community",
      "venue_type": "venue",
      "day": "day1",
      "event_name": "nswer_change_up",
      "event_date": "",
      "location": "演唱會現場",
      "support_items": "瓶蓋徽章",
      "quantity": "100",
      "conditions": "出示粉絲證明即可",
      "distribution_time": "",
      "contact": "https://www.threads.com/@nswer_change_up/post/DY2Mpgfkvnn"
    },
    {
      "id": "community_312022",
      "username": "_yn.731",
      "text": "_yn.731\n@arzhuang1ndah0us3 和 @_yn.731 聯合應援\n\n✮手機不能掉吧—手機掛繩*90\n（每位成員15條，當天「隨機」發送）\n（壓克力吊飾為自繪，顏色存在些許誤差）\n（圖片皆為預覽打樣）\n✮進場要先外貌check—摺疊氣墊梳*30\n（上面除了團體名稱外的裝飾貼紙為隨機，大家拿到的款式都會不同）\n（因為我們是二人作業，大家都能拿到獨一無二的😍）",
      "url": "https://www.threads.com/@_yn.731/post/DY3WKCHgHmR",
      "date": "2026/05/28",
      "source": "community",
      "venue_type": "venue",
      "day": "day2",
      "event_name": "_yn.731",
      "event_date": "",
      "location": "演唱會現場",
      "support_items": "手機掛繩、摺疊氣墊梳",
      "quantity": "數量看說明",
      "conditions": "✮出示任何粉絲證明（小卡/手燈/娃娃/泡泡）\n✮追蹤NMIXX官方IG\n✮一人限領一組（手機掛繩*1+氣墊梳*1）若氣墊梳發完則一人限領一條手機掛繩",
      "distribution_time": "",
      "contact": "https://www.threads.com/@_yn.731/post/DY3WKCHgHmR"
    },
    {
      "id": "community_101003",
      "username": "nswer_jaejane",
      "text": "🐦\n@nswer_jaejane 和@squirrel_toy 聯合應援\n",
      "url": "https://www.threads.com/@nswer_jaejane/post/DY4Hee5FGnY",
      "date": "2026/05/28",
      "source": "community",
      "venue_type": "venue",
      "day": "both",
      "event_name": "🐦",
      "event_date": "",
      "location": "演唱會現場",
      "support_items": "奶油黃色絲帶",
      "quantity": "50",
      "conditions": "1.任意粉絲證明\n2.追蹤我們兩個or @diving_with_nmixx\n",
      "distribution_time": "",
      "contact": "https://www.threads.com/@nswer_jaejane/post/DY4Hee5FGnY"
    }
  ]
}