{
  "pending": [
    {
      "id": "community_539311",
      "username": "yirou_.lily_.lix",
      "text": "1. 一人一份不可代領\n2. 領取後不要隨意丟棄\n3. 徽章是印刷的，可能有汙點，完美主義者請繞道",
      "url": "https://www.threads.com/@yirou_.lily_.lix/post/Dah8W78EauQ",
      "urls": [
        "https://www.threads.com/@yirou_.lily_.lix/post/Dah8W78EauQ"
      ],
      "date": "2026/07/08",
      "source": "community",
      "venue_type": "venue",
      "day": "day2",
      "event_name": "𝑹𝒐𝒖‧˚₊☆",
      "event_date": "",
      "location": "演唱會現場（時間地點待定，當天於此帳號公布）",
      "support_items": " 莉莉、海嫄徽章",
      "quantity": "請查看原文",
      "conditions": "1. 追蹤 nmixx_official\n2. 出示證明（娃娃、小卡、手燈...）\n3. 有一顆愛 NMIXX 的心",
      "distribution_time": "",
      "contact": "https://www.threads.com/@yirou_.lily_.lix/post/Dah8W78EauQ"
    }
  ]
}