{
  "pending": [
    {
      "id": "community_236488",
      "username": "iamzuhasdog",
      "text": "除了兩隻稍微描了圖其他全都手搓，第一次做應援又只會畫纏繞畫，沒畫得很好但希望大家喜歡。",
      "url": "https://www.threads.com/@iamzuhasdog/post/DZCXuhPFIa6",
      "date": "2026/06/07",
      "source": "community",
      "venue_type": "venue",
      "day": "day1",
      "event_name": "阿久",
      "event_date": "",
      "location": "演唱會場外",
      "support_items": "裴真率應援小圓鏡",
      "quantity": "20 個",
      "conditions": "需出示阿裴泡泡 / 手燈 / 小卡之類的證明",
      "distribution_time": "",
      "contact": "https://www.threads.com/@iamzuhasdog/post/DZCXuhPFIa6"
    },
    {
      "id": "community_82095",
      "username": "c.ting_yu_",
      "text": "瑜\nHeavy Serenade MV 元素設計，材料為海邊碎石與珍珠（呼應 MIXXPOP 大膽 MIX 風格）。\n項鍊上六組珍珠每組兩顆，寓意團體出道日 2022/2/22 中的六個 2，也象徵六位成員（你看見 O.O 了嗎？）。\n珍珠泛彩虹光澤而非純白，象徵真摯、自由奔放的愛。\n圓形鳥巢吊墜象徵出道日中唯一的 0，也是初踏上 MIXXTOPIA 的荒蕪與未知，後來用愛滋養出生機；烏巢裡的蛋即是星球上萬物生命的起點，一旁盛放的花朵則是六人心中正在蓬勃生長、永不枯竭的愛。",
      "url": "https://www.threads.com/@c.ting_yu_/post/DZHjDgsCRWf",
      "date": "2026/06/07",
      "source": "community",
      "venue_type": "venue",
      "day": "both",
      "event_name": "瑜",
      "event_date": "",
      "location": "未公告",
      "support_items": "項鍊",
      "quantity": "未定",
      "conditions": "未公布",
      "distribution_time": "未定",
      "contact": "https://www.threads.com/@c.ting_yu_/post/DZHjDgsCRWf"
    },
    {
      "id": "community_908984",
      "username": "zx_.217",
      "text": "ㄔ余子車干\n規格 7.5mm × 7.5mm。學測生無法出席演唱會，7/11 由 @ympm16_yn26 代發。\n交換應援部分可能少量（可選成員），可先放留言區（因朋友也有應援要發可能會小忙）。\n另有留少量應援會開線上 20 不內退但可選成員。時間會再公布。",
      "url": "https://www.threads.com/@zx_.217/post/DZM7ml9jwlU",
      "date": "2026/06/07",
      "source": "community",
      "venue_type": "venue",
      "day": "day1",
      "event_name": "ㄔ余子車干",
      "event_date": "",
      "location": "後續會同步更新",
      "support_items": "小圓鏡",
      "quantity": "每位成員各 20 個（共 120 個）",
      "conditions": "統一用抽選領取（無門檻）",
      "distribution_time": "",
      "contact": "https://www.threads.com/@zx_.217/post/DZM7ml9jwlU"
    }
  ]
}