{
  "pending": [
    {
      "id": "community_846726",
      "username": "caiwen_1025",
      "text": "1. 付費應援 $50/1，高於成本部分會以 NSWER 名義捐出（附證明）\n2. 單獨印製壓克力片 + 手工組裝\n3. 可挑款但部分包成盲包（友善團粉 & 選擇困難）\n4. 有手作痕跡\n5. 會視反應決定是否限購\n6. 圖片僅供參考\n7. 保有一切解釋權\n8. 特別感謝繪師：南阿圈",
      "url": "https://www.threads.com/@caiwen_1025/post/DZhxFgoEgfn",
      "urls": [
        "https://www.threads.com/@caiwen_1025/post/DZhxFgoEgfn"
      ],
      "date": "2026/07/04",
      "source": "community",
      "venue_type": "venue",
      "day": "day1",
      "event_name": "香菇蚊o.o",
      "event_date": "",
      "location": "演唱會現場",
      "support_items": "髮夾",
      "quantity": "7 款各 14 個（共 98 個）",
      "conditions": "1. 出示此篇貼文\n2. 需要費用，請洽原文",
      "distribution_time": "",
      "contact": "https://www.threads.com/@caiwen_1025/post/DZhxFgoEgfn"
    },
    {
      "id": "community_397294",
      "username": "udn.0516_nswer",
      "text": "1. 海嫄中背吊飾 + 團體反轉膠片\n2. 一人限領一份\n3. 禁止代領、轉售",
      "url": "https://www.threads.com/@udn.0516_nswer/post/DaXWLzck_j5",
      "urls": [
        "https://www.threads.com/@udn.0516_nswer/post/DaXWLzck_j5"
      ],
      "date": "2026/07/04",
      "source": "community",
      "venue_type": "venue",
      "day": "day1",
      "event_name": "udn.__.",
      "event_date": "",
      "location": "演唱會現場（當天發文公布）",
      "support_items": "吊飾、膠片",
      "quantity": "20 份",
      "conditions": "1. 出示粉絲證明（IG 追蹤、手燈、小卡、娃娃…皆可）",
      "distribution_time": "",
      "contact": "https://www.threads.com/@udn.0516_nswer/post/DaXWLzck_j5"
    },
    {
      "id": "community_353432",
      "username": "ohaewrong",
      "text": "1. 規格 340×380mm\n2. 數量有限派完即止\n3. 禁私下轉售、禁代人領取",
      "url": "https://www.threads.com/@ohaewrong/post/DaXeilykoSi",
      "urls": [
        "https://www.threads.com/@ohaewrong/post/DaXeilykoSi"
      ],
      "date": "2026/07/04",
      "source": "community",
      "venue_type": "venue",
      "day": "day2",
      "event_name": "誤會員",
      "event_date": "",
      "location": "演唱會現場（請留意當日限時動態及 Threads 更新）",
      "support_items": "帆布袋",
      "quantity": "請查看原文",
      "conditions": "1. 先到先得，不設預留",
      "distribution_time": "",
      "contact": "https://www.threads.com/@ohaewrong/post/DaXeilykoSi"
    },
    {
      "id": "community_375369",
      "username": "r.taro._yyyj",
      "text": "1. 水母吊飾（後面有別針可別在包包上）\n2. 有一定手作感，每個水母有些微不同\n3. 希望收到的人真心喜歡\n4. 反應好會再多做",
      "url": "https://www.threads.com/@r.taro._yyyj/post/DaXPnFugW4O",
      "urls": [
        "https://www.threads.com/@r.taro._yyyj/post/DaXPnFugW4O"
      ],
      "date": "2026/07/04",
      "source": "community",
      "venue_type": "venue",
      "day": "day2",
      "event_name": "小小Neverland",
      "event_date": "",
      "location": "演唱會現場（隨緣發放，行蹤不一定）",
      "support_items": "水母吊飾",
      "quantity": "請查看原文",
      "conditions": "請查看原文",
      "distribution_time": "",
      "contact": "https://www.threads.com/@r.taro._yyyj/post/DaXPnFugW4O"
    },
    {
      "id": "community_489410",
      "username": "teoe1120",
      "text": "1. 250ml 小罐水\n2. 韓場時做的貼紙一起發\n3. 兩樣一起發，沒特別想要哪個可以說\n4. 天氣炎熱請多補充水分",
      "url": "https://www.threads.com/@teoe1120/post/DaYCED2j-BD",
      "urls": [
        "https://www.threads.com/@teoe1120/post/DaYCED2j-BD"
      ],
      "date": "2026/07/04",
      "source": "community",
      "venue_type": "venue",
      "day": "both",
      "event_name": "teoe1120",
      "event_date": "",
      "location": "演唱會現場（當天再通知）",
      "support_items": "水、貼紙",
      "quantity": "水 45 罐/天（共 90）；貼紙 45 張/天（共 90）",
      "conditions": "請查看原文",
      "distribution_time": "",
      "contact": "https://www.threads.com/@teoe1120/post/DaYCED2j-BD"
    }
  ]
}